ecmind_blue_client_objdef/__init__.py
ecmind_blue_client_objdef/addons.py
ecmind_blue_client_objdef/cabinet.py
ecmind_blue_client_objdef/field.py
ecmind_blue_client_objdef/field_types.py
ecmind_blue_client_objdef/object.py
ecmind_blue_client_objdef/object_definition.py
ecmind_blue_client_objdef/table_column.py
ecmind_blue_client_objdef/table_field.py
ecmind_blue_client_objdef-0.1.2.dist-info/LICENSE
ecmind_blue_client_objdef-0.1.2.dist-info/METADATA
ecmind_blue_client_objdef-0.1.2.dist-info/WHEEL
ecmind_blue_client_objdef-0.1.2.dist-info/top_level.txt
ecmind_blue_client_objdef-0.1.2.dist-info/RECORD
