Metadata-Version: 2.1
Name: ecmind_blue_client_objdef
Version: 0.1.2
Summary: Helper modules for the `ecmind_blue_client` to ease the work with object definition APIs.
Home-page: https://gitlab.ecmind.ch/open/ecmind_blue_client_objdef
Author: Roland Koller
Author-email: info@ecmind.ch
Classifier: Programming Language :: Python :: 3
Classifier: License :: OSI Approved :: MIT License
Classifier: Operating System :: OS Independent
Requires-Python: >=3.9
License-File: LICENSE
Requires-Dist: ecmind-blue-client >=0.5.6
Requires-Dist: XmlElement >=0.3.2
